fewsats_logger/__init__.py
fewsats_logger/_modidx.py
fewsats_logger/core.py
fewsats_logger-0.0.3.dist-info/LICENSE
fewsats_logger-0.0.3.dist-info/METADATA
fewsats_logger-0.0.3.dist-info/WHEEL
fewsats_logger-0.0.3.dist-info/entry_points.txt
fewsats_logger-0.0.3.dist-info/top_level.txt
fewsats_logger-0.0.3.dist-info/RECORD
