Metadata-Version: 2.1
Name: fewsats-logger
Version: 0.0.3
Summary: Python Logger based on BetterStack
Home-page: https://github.com/Fewsats/fewsats-logger-py
Author: Pol Alvarez
Author-email: pol.avms@gmail.com
License: Apache Software License 2.0
Keywords: nbdev jupyter notebook python
Classifier: Development Status :: 4 - Beta
Classifier: Intended Audience :: Developers
Classifier: Natural Language :: English
Classifier: Programming Language :: Python :: 3.9
Classifier: Programming Language :: Python :: 3.10
Classifier: Programming Language :: Python :: 3.11
Classifier: Programming Language :: Python :: 3.12
Classifier: License :: OSI Approved :: Apache Software License
Requires-Python: >=3.9
License-File: LICENSE
Requires-Dist: logtail-python
Provides-Extra: dev
